Workbook

Sheet Dashboard
A1: FP&A Performance Dashboard — 2024
A2: Live KPIs, Budget vs Actual, Revenue Trend, and Variance Breakdown
R3: Month | S3: Budget | T3: Actual | V3: Month | W3: Revenue | Y3: Category | Z3: Base | AA3: Down | AB3: Up | AC3: Total | AD3: Variance
A4: Total Revenue | E4: Total Expenses | I4: Net Profit | M4: Overall Variance % | R4: Jan-2024 | S4: =SUMIFS('Raw Data'!C:C,'Raw Data'!B:B,R4) -> 3052110 | T4: =SUMIFS('Raw Data'!D:D,'Raw Data'!B:B,R4) -> 3066975 | V4: Jan-2024 | W4: =SUMIFS('Raw Data'!D:D,'Raw Data'!A:A,"Sales",'Raw Data'!B:B,V4) -> 267910 | Y4: Budget Total | Z4: 0 | AA4: 0 | AB4: 0 | AC4: =SUM('Raw Data'!C:C) -> 28221717 | AD4: =AC4 -> 28221717
A5: =SUMIFS('Raw Data'!D:D,'Raw Data'!A:A,"Sales") -> 3401641 | E5: =SUMIFS('Raw Data'!D:D,'Raw Data'!A:A,"<>Sales") -> 24770031 | I5: =SUMIFS('Raw Data'!D:D,'Raw Data'!A:A,"Sales")-SUMIFS('Raw Data'!D:D,'Raw Data'!A:A,"<>Sales") -> -21368390 | M5: =(SUM('Raw Data'!D:D)-SUM('Raw Data'!C:C))/SUM('Raw Data'!C:C) -> -0.0017732798 | R5: Feb-2024 | S5: =SUMIFS('Raw Data'!C:C,'Raw Data'!B:B,R5) -> 2091046 | T5: =SUMIFS('Raw Data'!D:D,'Raw Data'!B:B,R5) -> 2114500 | V5: Feb-2024 | W5: =SUMIFS('Raw Data'!D:D,'Raw Data'!A:A,"Sales",'Raw Data'!B:B,V5) -> 50926 | Y5: Sales | Z5: =AC4-AA5 -> 28130616 | AA5: =IF(AD5<0,-AD5,0) -> 91101 | AB5: =IF(AD5>0,AD5,0) -> 0 | AC5: 0 | AD5: =SUMIFS('Raw Data'!D:D,'Raw Data'!A:A,Y5)-SUMIFS('Raw Data'!C:C,'Raw Data'!A:A,Y5) -> -91101
R6: Mar-2024 | S6: =SUMIFS('Raw Data'!C:C,'Raw Data'!B:B,R6) -> 2638708 | T6: =SUMIFS('Raw Data'!D:D,'Raw Data'!B:B,R6) -> 2721812 | V6: Mar-2024 | W6: =SUMIFS('Raw Data'!D:D,'Raw Data'!A:A,"Sales",'Raw Data'!B:B,V6) -> 53012 | Y6: Marketing | Z6: =Z5+AC5+AB5-AA5-AA6 -> 28039515 | AA6: =IF(AD6<0,-AD6,0) -> 0 | AB6: =IF(AD6>0,AD6,0) -> 88118 | AC6: 0 | AD6: =SUMIFS('Raw Data'!D:D,'Raw Data'!A:A,Y6)-SUMIFS('Raw Data'!C:C,'Raw Data'!A:A,Y6) -> 88118
A7: Charts | R7: Apr-2024 | S7: =SUMIFS('Raw Data'!C:C,'Raw Data'!B:B,R7) -> 2687968 | T7: =SUMIFS('Raw Data'!D:D,'Raw Data'!B:B,R7) -> 2764291 | V7: Apr-2024 | W7: =SUMIFS('Raw Data'!D:D,'Raw Data'!A:A,"Sales",'Raw Data'!B:B,V7) -> 18392 | Y7: Operations | Z7: =Z6+AC6+AB6-AA6-AA7 -> 28127633 | AA7: =IF(AD7<0,-AD7,0) -> 0 | AB7: =IF(AD7>0,AD7,0) -> 12510 | AC7: 0 | AD7: =SUMIFS('Raw Data'!D:D,'Raw Data'!A:A,Y7)-SUMIFS('Raw Data'!C:C,'Raw Data'!A:A,Y7) -> 12510
R8: May-2024 | S8: =SUMIFS('Raw Data'!C:C,'Raw Data'!B:B,R8) -> 1585925 | T8: =SUMIFS('Raw Data'!D:D,'Raw Data'!B:B,R8) -> 1576768 | V8: May-2024 | W8: =SUMIFS('Raw Data'!D:D,'Raw Data'!A:A,"Sales",'Raw Data'!B:B,V8) -> 602361 | Y8: R&D | Z8: =Z7+AC7+AB7-AA7-AA8 -> 28025764 | AA8: =IF(AD8<0,-AD8,0) -> 114379 | AB8: =IF(AD8>0,AD8,0) -> 0 | AC8: 0 | AD8: =SUMIFS('Raw Data'!D:D,'Raw Data'!A:A,Y8)-SUMIFS('Raw Data'!C:C,'Raw Data'!A:A,Y8) -> -114379
R9: Jun-2024 | S9: =SUMIFS('Raw Data'!C:C,'Raw Data'!B:B,R9) -> 1508713 | T9: =SUMIFS('Raw Data'!D:D,'Raw Data'!B:B,R9) -> 1518273 | V9: Jun-2024 | W9: =SUMIFS('Raw Data'!D:D,'Raw Data'!A:A,"Sales",'Raw Data'!B:B,V9) -> 291770 | Y9: HR | Z9: =Z8+AC8+AB8-AA8-AA9 -> 27911385 | AA9: =IF(AD9<0,-AD9,0) -> 0 | AB9: =IF(AD9>0,AD9,0) -> 29269 | AC9: 0 | AD9: =SUMIFS('Raw Data'!D:D,'Raw Data'!A:A,Y9)-SUMIFS('Raw Data'!C:C,'Raw Data'!A:A,Y9) -> 29269
R10: Jul-2024 | S10: =SUMIFS('Raw Data'!C:C,'Raw Data'!B:B,R10) -> 2270552 | T10: =SUMIFS('Raw Data'!D:D,'Raw Data'!B:B,R10) -> 2308696 | V10: Jul-2024 | W10: =SUMIFS('Raw Data'!D:D,'Raw Data'!A:A,"Sales",'Raw Data'!B:B,V10) -> 358292 | Y10: Customer Success | Z10: =Z9+AC9+AB9-AA9-AA10 -> 27888914 | AA10: =IF(AD10<0,-AD10,0) -> 51740 | AB10: =IF(AD10>0,AD10,0) -> 0 | AC10: 0 | AD10: =SUMIFS('Raw Data'!D:D,'Raw Data'!A:A,Y10)-SUMIFS('Raw Data'!C:C,'Raw Data'!A:A,Y10) -> -51740
R11: Aug-2024 | S11: =SUMIFS('Raw Data'!C:C,'Raw Data'!B:B,R11) -> 1150159 | T11: =SUMIFS('Raw Data'!D:D,'Raw Data'!B:B,R11) -> 1161626 | V11: Aug-2024 | W11: =SUMIFS('Raw Data'!D:D,'Raw Data'!A:A,"Sales",'Raw Data'!B:B,V11) -> 6230 | Y11: Finance | Z11: =Z10+AC10+AB10-AA10-AA11 -> 27837174 | AA11: =IF(AD11<0,-AD11,0) -> 0 | AB11: =IF(AD11>0,AD11,0) -> 25962 | AC11: 0 | AD11: =SUMIFS('Raw Data'!D:D,'Raw Data'!A:A,Y11)-SUMIFS('Raw Data'!C:C,'Raw Data'!A:A,Y11) -> 25962
R12: Sep-2024 | S12: =SUMIFS('Raw Data'!C:C,'Raw Data'!B:B,R12) -> 2077720 | T12: =SUMIFS('Raw Data'!D:D,'Raw Data'!B:B,R12) -> 2021132 | V12: Sep-2024 | W12: =SUMIFS('Raw Data'!D:D,'Raw Data'!A:A,"Sales",'Raw Data'!B:B,V12) -> 1064056 | Y12: IT | Z12: =Z11+AC11+AB11-AA11-AA12 -> 27863136 | AA12: =IF(AD12<0,-AD12,0) -> 0 | AB12: =IF(AD12>0,AD12,0) -> 51316 | AC12: 0 | AD12: =SUMIFS('Raw Data'!D:D,'Raw Data'!A:A,Y12)-SUMIFS('Raw Data'!C:C,'Raw Data'!A:A,Y12) -> 51316
R13: Oct-2024 | S13: =SUMIFS('Raw Data'!C:C,'Raw Data'!B:B,R13) -> 3233538 | T13: =SUMIFS('Raw Data'!D:D,'Raw Data'!B:B,R13) -> 3132891 | V13: Oct-2024 | W13: =SUMIFS('Raw Data'!D:D,'Raw Data'!A:A,"Sales",'Raw Data'!B:B,V13) -> 551528 | Y13: Actual Total | Z13: 0 | AA13: 0 | AB13: 0 | AC13: =SUM('Raw Data'!D:D) -> 28171672 | AD13: =AC13-AC4 -> -50045
R14: Nov-2024 | S14: =SUMIFS('Raw Data'!C:C,'Raw Data'!B:B,R14) -> 2744003 | T14: =SUMIFS('Raw Data'!D:D,'Raw Data'!B:B,R14) -> 2675953 | V14: Nov-2024 | W14: =SUMIFS('Raw Data'!D:D,'Raw Data'!A:A,"Sales",'Raw Data'!B:B,V14) -> 78090
R15: Dec-2024 | S15: =SUMIFS('Raw Data'!C:C,'Raw Data'!B:B,R15) -> 3181275 | T15: =SUMIFS('Raw Data'!D:D,'Raw Data'!B:B,R15) -> 3108755 | V15: Dec-2024 | W15: =SUMIFS('Raw Data'!D:D,'Raw Data'!A:A,"Sales",'Raw Data'!B:B,V15) -> 59074

Sheet Raw Data
A1: Department | B1: Month | C1: Budget | D1: Actual | E1: Variance | F1: Variance %
A2: Sales | B2: Jan-2024 | C2: 284101 | D2: 267910 | E2: =D2-C2 -> -16191 | F2: =IFERROR(E2/C2,0) -> -0.056990296
A3: Sales | B3: Feb-2024 | C3: 52786 | D3: 50926 | E3: =D3-C3 -> -1860 | F3: =IFERROR(E3/C3,0) -> -0.035236616
A4: Sales | B4: Mar-2024 | C4: 52777 | D4: 53012 | E4: =D4-C4 -> 235 | F4: =IFERROR(E4/C4,0) -> 0.0044526972
A5: Sales | B5: Apr-2024 | C5: 18621 | D5: 18392 | E5: =D5-C5 -> -229 | F5: =IFERROR(E5/C5,0) -> -0.012297943
A6: Sales | B6: May-2024 | C6: 625881 | D6: 602361 | E6: =D6-C6 -> -23520 | F6: =IFERROR(E6/C6,0) -> -0.037579029
A7: Sales | B7: Jun-2024 | C7: 286012 | D7: 291770 | E7: =D7-C7 -> 5758 | F7: =IFERROR(E7/C7,0) -> 0.020132022
A8: Sales | B8: Jul-2024 | C8: 383156 | D8: 358292 | E8: =D8-C8 -> -24864 | F8: =IFERROR(E8/C8,0) -> -0.064892629
A9: Sales | B9: Aug-2024 | C9: 6473 | D9: 6230 | E9: =D9-C9 -> -243 | F9: =IFERROR(E9/C9,0) -> -0.037540553
A10: Sales | B10: Sep-2024 | C10: 1090283 | D10: 1064056 | E10: =D10-C10 -> -26227 | F10: =IFERROR(E10/C10,0) -> -0.024055222
A11: Sales | B11: Oct-2024 | C11: 555924 | D11: 551528 | E11: =D11-C11 -> -4396 | F11: =IFERROR(E11/C11,0) -> -0.0079075557
A12: Sales | B12: Nov-2024 | C12: 74278 | D12: 78090 | E12: =D12-C12 -> 3812 | F12: =IFERROR(E12/C12,0) -> 0.051320714
A13: Sales | B13: Dec-2024 | C13: 62450 | D13: 59074 | E13: =D13-C13 -> -3376 | F13: =IFERROR(E13/C13,0) -> -0.054059247
... A97: IT | B97: Dec-2024 | C97: 44481 | D97: 47290 | E97: =D97-C97 -> 2809 | F97: =IFERROR(E97/C97,0) -> 0.063150559

Sheet Monthly P&L
A1: Monthly P&L — Budget vs. Actual
A3: Line Item | B3: Jan-2024 | F3: Feb-2024 | J3: Mar-2024 | N3: Apr-2024 | R3: May-2024 | V3: Jun-2024 | Z3: Jul-2024 | AD3: Aug-2024 | AH3: Sep-2024 | AL3: Oct-2024 | AP3: Nov-2024 | AT3: Dec-2024
B4: Budget | C4: Actual | D4: Variance | E4: Var % | F4: Budget | G4: Actual | H4: Variance | I4: Var % | J4: Budget | K4: Actual | L4: Variance | M4: Var % | N4: Budget | O4: Actual | P4: Variance | Q4: Var % | R4: Budget | S4: Actual | T4: Variance | U4: Var % | V4: Budget | W4: Actual | X4: Variance | Y4: Var % | Z4: Budget | AA4: Actual | AB4: Variance | AC4: Var % | AD4: Budget | AE4: Actual | AF4: Variance | AG4: Var % | AH4: Budget | AI4: Actual | AJ4: Variance | AK4: Var % | AL4: Budget | AM4: Actual | AN4: Variance | AO4: Var % | AP4: Budget | AQ4: Actual | AR4: Variance | AS4: Var % | AT4: Budget | AU4: Actual | AV4: Variance | AW4: Var %
A5: Revenue
A6: Sales | B6: 284101 | C6: 267910 | D6: =C6-B6 -> -16191 | E6: =IFERROR(D6/B6,0) -> -0.056990296 | F6: 52786 | G6: 50926 | H6: =G6-F6 -> -1860 | I6: =IFERROR(H6/F6,0) -> -0.035236616 | J6: 52777 | K6: 53012 | L6: =K6-J6 -> 235 | M6: =IFERROR(L6/J6,0) -> 0.0044526972 | N6: 18621 | O6: 18392 | P6: =O6-N6 -> -229 | Q6: =IFERROR(P6/N6,0) -> -0.012297943 | R6: 625881 | S6: 602361 | T6: =S6-R6 -> -23520 | U6: =IFERROR(T6/R6,0) -> -0.037579029 | V6: 286012 | W6: 291770 | X6: =W6-V6 -> 5758 | Y6: =IFERROR(X6/V6,0) -> 0.020132022 | Z6: 383156 | AA6: 358292 | AB6: =AA6-Z6 -> -24864 | AC6: =IFERROR(AB6/Z6,0) -> -0.064892629 | AD6: 6473 | AE6: 6230 | AF6: =AE6-AD6 -> -243 | AG6: =IFERROR(AF6/AD6,0) -> -0.037540553 | AH6: 1090283 | AI6: 1064056 | AJ6: =AI6-AH6 -> -26227 | AK6: =IFERROR(AJ6/AH6,0) -> -0.024055222 | AL6: 555924 | AM6: 551528 | AN6: =AM6-AL6 -> -4396 | AO6: =IFERROR(AN6/AL6,0) -> -0.0079075557 | AP6: 74278 | AQ6: 78090 | AR6: =AQ6-AP6 -> 3812 | AS6: =IFERROR(AR6/AP6,0) -> 0.051320714 | AT6: 62450 | AU6: 59074 | AV6: =AU6-AT6 -> -3376 | AW6: =IFERROR(AV6/AT6,0) -> -0.054059247
A7: Costs
A8: Marketing | B8: 1310207 | C8: 1353427 | D8: =C8-B8 -> 43220 | E8: =IFERROR(D8/B8,0) -> 0.032987154 | F8: 201517 | G8: 205506 | H8: =G8-F8 -> 3989 | I8: =IFERROR(H8/F8,0) -> 0.019794856 | J8: 629971 | K8: 667753 | L8: =K8-J8 -> 37782 | M8: =IFERROR(L8/J8,0) -> 0.059974189 | N8: 365478 | O8: 343989 | P8: =O8-N8 -> -21489 | Q8: =IFERROR(P8/N8,0) -> -0.058796973 | R8: 191888 | S8: 188125 | T8: =S8-R8 -> -3763 | U8: =IFERROR(T8/R8,0) -> -0.019610398 | V8: 4280 | W8: 4035 | X8: =W8-V8 -> -245 | Y8: =IFERROR(X8/V8,0) -> -0.057242991 | Z8: 913634 | AA8: 955629 | AB8: =AA8-Z8 -> 41995 | AC8: =IFERROR(AB8/Z8,0) -> 0.045964796 | AD8: 265515 | AE8: 261937 | AF8: =AE8-AD8 -> -3578 | AG8: =IFERROR(AF8/AD8,0) -> -0.013475698 | AH8: 156015 | AI8: 147813 | AJ8: =AI8-AH8 -> -8202 | AK8: =IFERROR(AJ8/AH8,0) -> -0.052571868 | AL8: 5158 | AM8: 5220 | AN8: =AM8-AL8 -> 62 | AO8: =IFERROR(AN8/AL8,0) -> 0.012020163 | AP8: 84135 | AQ8: 77037 | AR8: =AQ8-AP8 -> -7098 | AS8: =IFERROR(AR8/AP8,0) -> -0.084364414 | AT8: 88385 | AU8: 93830 | AV8: =AU8-AT8 -> 5445 | AW8: =IFERROR(AV8/AT8,0) -> 0.061605476
A9: Operations | B9: 936211 | C9: 899294 | D9: =C9-B9 -> -36917 | E9: =IFERROR(D9/B9,0) -> -0.03943235 | F9: 751664 | G9: 757440 | H9: =G9-F9 -> 5776 | I9: =IFERROR(H9/F9,0) -> 0.0076842845 | J9: 304068 | K9: 284414 | L9: =K9-J9 -> -19654 | M9: =IFERROR(L9/J9,0) -> -0.064636858 | N9: 850883 | O9: 897167 | P9: =O9-N9 -> 46284 | Q9: =IFERROR(P9/N9,0) -> 0.054395258 | R9: 30924 | S9: 28555 | T9: =S9-R9 -> -2369 | U9: =IFERROR(T9/R9,0) -> -0.076607166 | V9: 72803 | W9: 79183 | X9: =W9-V9 -> 6380 | Y9: =IFERROR(X9/V9,0) -> 0.087633751 | Z9: 15447 | AA9: 16203 | AB9: =AA9-Z9 -> 756 | AC9: =IFERROR(AB9/Z9,0) -> 0.048941542 | AD9: 131343 | AE9: 124220 | AF9: =AE9-AD9 -> -7123 | AG9: =IFERROR(AF9/AD9,0) -> -0.054232049 | AH9: 164250 | AI9: 149630 | AJ9: =AI9-AH9 -> -14620 | AK9: =IFERROR(AJ9/AH9,0) -> -0.089010654 | AL9: 105653 | AM9: 111652 | AN9: =AM9-AL9 -> 5999 | AO9: =IFERROR(AN9/AL9,0) -> 0.056780214 | AP9: 588928 | AQ9: 610856 | AR9: =AQ9-AP9 -> 21928 | AS9: =IFERROR(AR9/AP9,0) -> 0.037233754 | AT9: 147261 | AU9: 153331 | AV9: =AU9-AT9 -> 6070 | AW9: =IFERROR(AV9/AT9,0) -> 0.041219332
A10: R&D | B10: 32179 | C10: 32018 | D10: =C10-B10 -> -161 | E10: =IFERROR(D10/B10,0) -> -0.005003263 | F10: 185677 | G10: 172963 | H10: =G10-F10 -> -12714 | I10: =IFERROR(H10/F10,0) -> -0.068473747 | J10: 51513 | K10: 53490 | L10: =K10-J10 -> 1977 | M10: =IFERROR(L10/J10,0) -> 0.038378662 | N10: 831785 | O10: 870830 | P10: =O10-N10 -> 39045 | Q10: =IFERROR(P10/N10,0) -> 0.046941217 | R10: 408379 | S10: 412883 | T10: =S10-R10 -> 4504 | U10: =IFERROR(T10/R10,0) -> 0.011028971 | V10: 168077 | W10: 176274 | X10: =W10-V10 -> 8197 | Y10: =IFERROR(X10/V10,0) -> 0.048769314 | Z10: 27468 | AA10: 27437 | AB10: =AA10-Z10 -> -31 | AC10: =IFERROR(AB10/Z10,0) -> -0.001128586 | AD10: 155809 | AE10: 156446 | AF10: =AE10-AD10 -> 637 | AG10: =IFERROR(AF10/AD10,0) -> 0.0040883389 | AH10: 164520 | AI10: 162374 | AJ10: =AI10-AH10 -> -2146 | AK10: =IFERROR(AJ10/AH10,0) -> -0.013044007 | AL10: 547074 | AM10: 500340 | AN10: =AM10-AL10 -> -46734 | AO10: =IFERROR(AN10/AL10,0) -> -0.085425372 | AP10: 424520 | AQ10: 394557 | AR10: =AQ10-AP10 -> -29963 | AS10: =IFERROR(AR10/AP10,0) -> -0.070580891 | AT10: 912818 | AU10: 835828 | AV10: =AU10-AT10 -> -76990 | AW10: =IFERROR(AV10/AT10,0) -> -0.08434321
A11: HR | B11: 176168 | C11: 180398 | D11: =C11-B11 -> 4230 | E11: =IFERROR(D11/B11,0) -> 0.024011171 | F11: 331631 | G11: 353804 | H11: =G11-F11 -> 22173 | I11: =IFERROR(H11/F11,0) -> 0.066860456 | J11: 1111570 | K11: 1172329 | L11: =K11-J11 -> 60759 | M11: =IFERROR(L11/J11,0) -> 0.054660525 | N11: 133849 | O11: 126297 | P11: =O11-N11 -> -7552 | Q11: =IFERROR(P11/N11,0) -> -0.056421789 | R11: 246601 | S11: 264025 | T11: =S11-R11 -> 17424 | U11: =IFERROR(T11/R11,0) -> 0.070656648 | V11: 657601 | W11: 662257 | X11: =W11-V11 -> 4656 | Y11: =IFERROR(X11/V11,0) -> 0.0070802812 | Z11: 121277 | AA11: 127988 | AB11: =AA11-Z11 -> 6711 | AC11: =IFERROR(AB11/Z11,0) -> 0.055336131 | AD11: 37393 | AE11: 40058 | AF11: =AE11-AD11 -> 2665 | AG11: =IFERROR(AF11/AD11,0) -> 0.071270024 | AH11: 159710 | AI11: 154478 | AJ11: =AI11-AH11 -> -5232 | AK11: =IFERROR(AJ11/AH11,0) -> -0.032759376 | AL11: 82067 | AM11: 76306 | AN11: =AM11-AL11 -> -5761 | AO11: =IFERROR(AN11/AL11,0) -> -0.07019874 | AP11: 1239326 | AQ11: 1178634 | AR11: =AQ11-AP11 -> -60692 | AS11: =IFERROR(AR11/AP11,0) -> -0.04897178 | AT11: 770631 | AU11: 760519 | AV11: =AU11-AT11 -> -10112 | AW11: =IFERROR(AV11/AT11,0) -> -0.013121715
A12: Customer Success | B12: 1363 | C12: 1476 | D12: =C12-B12 -> 113 | E12: =IFERROR(D12/B12,0) -> 0.082905356 | F12: 139699 | G12: 133457 | H12: =G12-F12 -> -6242 | I12: =IFERROR(H12/F12,0) -> -0.04468178 | J12: 105579 | K12: 105526 | L12: =K12-J12 -> -53 | M12: =IFERROR(L12/J12,0) -> -0.00050199377 | N12: 49083 | O12: 47323 | P12: =O12-N12 -> -1760 | Q12: =IFERROR(P12/N12,0) -> -0.035857629 | R12: 24951 | S12: 23984 | T12: =S12-R12 -> -967 | U12: =IFERROR(T12/R12,0) -> -0.038755962 | V12: 80494 | W12: 73783 | X12: =W12-V12 -> -6711 | Y12: =IFERROR(X12/V12,0) -> -0.083372674 | Z12: 559505 | AA12: 570539 | AB12: =AA12-Z12 -> 11034 | AC12: =IFERROR(AB12/Z12,0) -> 0.019721003 | AD12: 76288 | AE12: 76324 | AF12: =AE12-AD12 -> 36 | AG12: =IFERROR(AF12/AD12,0) -> 0.00047189597 | AH12: 142939 | AI12: 131398 | AJ12: =AI12-AH12 -> -11541 | AK12: =IFERROR(AJ12/AH12,0) -> -0.080740736 | AL12: 237254 | AM12: 227800 | AN12: =AM12-AL12 -> -9454 | AO12: =IFERROR(AN12/AL12,0) -> -0.03984759 | AP12: 88324 | AQ12: 94814 | AR12: =AQ12-AP12 -> 6490 | AS12: =IFERROR(AR12/AP12,0) -> 0.073479462 | AT12: 697211 | AU12: 664526 | AV12: =AU12-AT12 -> -32685 | AW12: =IFERROR(AV12/AT12,0) -> -0.046879639
A13: Finance | B13: 204546 | C13: 215530 | D13: =C13-B13 -> 10984 | E13: =IFERROR(D13/B13,0) -> 0.053699412 | F13: 160450 | G13: 150362 | H13: =G13-F13 -> -10088 | I13: =IFERROR(H13/F13,0) -> -0.062873169 | J13: 217501 | K13: 217821 | L13: =K13-J13 -> 320 | M13: =IFERROR(L13/J13,0) -> 0.0014712576 | N13: 242694 | O13: 251248 | P13: =O13-N13 -> 8554 | Q13: =IFERROR(P13/N13,0) -> 0.03524603 | R13: 22781 | S13: 24250 | T13: =S13-R13 -> 1469 | U13: =IFERROR(T13/R13,0) -> 0.064483561 | V13: 124695 | W13: 120788 | X13: =W13-V13 -> -3907 | Y13: =IFERROR(X13/V13,0) -> -0.031332451 | Z13: 74922 | AA13: 71149 | AB13: =AA13-Z13 -> -3773 | AC13: =IFERROR(AB13/Z13,0) -> -0.05035904 | AD13: 439148 | AE13: 455838 | AF13: =AE13-AD13 -> 16690 | AG13: =IFERROR(AF13/AD13,0) -> 0.03800541 | AH13: 171698 | AI13: 181263 | AJ13: =AI13-AH13 -> 9565 | AK13: =IFERROR(AJ13/AH13,0) -> 0.055708278 | AL13: 1107759 | AM13: 1077583 | AN13: =AM13-AL13 -> -30176 | AO13: =IFERROR(AN13/AL13,0) -> -0.027240582 | AP13: 137497 | AQ13: 127502 | AR13: =AQ13-AP13 -> -9995 | AS13: =IFERROR(AR13/AP13,0) -> -0.072692495 | AT13: 458038 | AU13: 494357 | AV13: =AU13-AT13 -> 36319 | AW13: =IFERROR(AV13/AT13,0) -> 0.079292548
A14: IT | B14: 107335 | C14: 116922 | D14: =C14-B14 -> 9587 | E14: =IFERROR(D14/B14,0) -> 0.089318489 | F14: 267622 | G14: 290042 | H14: =G14-F14 -> 22420 | I14: =IFERROR(H14/F14,0) -> 0.083774877 | J14: 165729 | K14: 167467 | L14: =K14-J14 -> 1738 | M14: =IFERROR(L14/J14,0) -> 0.010487 | N14: 195575 | O14: 209045 | P14: =O14-N14 -> 13470 | Q14: =IFERROR(P14/N14,0) -> 0.068873834 | R14: 34520 | S14: 32585 | T14: =S14-R14 -> -1935 | U14: =IFERROR(T14/R14,0) -> -0.056054461 | V14: 114751 | W14: 110183 | X14: =W14-V14 -> -4568 | Y14: =IFERROR(X14/V14,0) -> -0.039807932 | Z14: 175143 | AA14: 181459 | AB14: =AA14-Z14 -> 6316 | AC14: =IFERROR(AB14/Z14,0) -> 0.036061961 | AD14: 38190 | AE14: 40573 | AF14: =AE14-AD14 -> 2383 | AG14: =IFERROR(AF14/AD14,0) -> 0.062398534 | AH14: 28305 | AI14: 30120 | AJ14: =AI14-AH14 -> 1815 | AK14: =IFERROR(AJ14/AH14,0) -> 0.064122946 | AL14: 592649 | AM14: 582462 | AN14: =AM14-AL14 -> -10187 | AO14: =IFERROR(AN14/AL14,0) -> -0.017188926 | AP14: 106995 | AQ14: 114463 | AR14: =AQ14-AP14 -> 7468 | AS14: =IFERROR(AR14/AP14,0) -> 0.069797654 | AT14: 44481 | AU14: 47290 | AV14: =AU14-AT14 -> 2809 | AW14: =IFERROR(AV14/AT14,0) -> 0.063150559
A15: Total Costs | B15: =SUM(B8,B9,B10,B11,B12,B13,B14) -> 2768009 | C15: =SUM(C8,C9,C10,C11,C12,C13,C14) -> 2799065 | D15: =C15-B15 -> 31056 | E15: =IFERROR(D15/B15,0) -> 0.011219617 | F15: =SUM(F8,F9,F10,F11,F12,F13,F14) -> 2038260 | G15: =SUM(G8,G9,G10,G11,G12,G13,G14) -> 2063574 | H15: =G15-F15 -> 25314 | I15: =IFERROR(H15/F15,0) -> 0.012419417 | J15: =SUM(J8,J9,J10,J11,J12,J13,J14) -> 2585931 | K15: =SUM(K8,K9,K10,K11,K12,K13,K14) -> 2668800 | L15: =K15-J15 -> 82869 | M15: =IFERROR(L15/J15,0) -> 0.032046099 | N15: =SUM(N8,N9,N10,N11,N12,N13,N14) -> 2669347 | O15: =SUM(O8,O9,O10,O11,O12,O13,O14) -> 2745899 | P15: =O15-N15 -> 76552 | Q15: =IFERROR(P15/N15,0) -> 0.028678175 | R15: =SUM(R8,R9,R10,R11,R12,R13,R14) -> 960044 | S15: =SUM(S8,S9,S10,S11,S12,S13,S14) -> 974407 | T15: =S15-R15 -> 14363 | U15: =IFERROR(T15/R15,0) -> 0.014960773 | V15: =SUM(V8,V9,V10,V11,V12,V13,V14) -> 1222701 | W15: =SUM(W8,W9,W10,W11,W12,W13,W14) -> 1226503 | X15: =W15-V15 -> 3802 | Y15: =IFERROR(X15/V15,0) -> 0.0031095092 | Z15: =SUM(Z8,Z9,Z10,Z11,Z12,Z13,Z14) -> 1887396 | AA15: =SUM(AA8,AA9,AA10,AA11,AA12,AA13,AA14) -> 1950404 | AB15: =AA15-Z15 -> 63008 | AC15: =IFERROR(AB15/Z15,0) -> 0.033383561 | AD15: =SUM(AD8,AD9,AD10,AD11,AD12,AD13,AD14) -> 1143686 | AE15: =SUM(AE8,AE9,AE10,AE11,AE12,AE13,AE14) -> 1155396 | AF15: =AE15-AD15 -> 11710 | AG15: =IFERROR(AF15/AD15,0) -> 0.010238824 | AH15: =SUM(AH8,AH9,AH10,AH11,AH12,AH13,AH14) -> 987437 | AI15: =SUM(AI8,AI9,AI10,AI11,AI12,AI13,AI14) -> 957076 | AJ15: =AI15-AH15 -> -30361 | AK15: =IFERROR(AJ15/AH15,0) -> -0.030747278 | AL15: =SUM(AL8,AL9,AL10,AL11,AL12,AL13,AL14) -> 2677614 | AM15: =SUM(AM8,AM9,AM10,AM11,AM12,AM13,AM14) -> 2581363 | AN15: =AM15-AL15 -> -96251 | AO15: =IFERROR(AN15/AL15,0) -> -0.035946555 | AP15: =SUM(AP8,AP9,AP10,AP11,AP12,AP13,AP14) -> 2669725 | AQ15: =SUM(AQ8,AQ9,AQ10,AQ11,AQ12,AQ13,AQ14) -> 2597863 | AR15: =AQ15-AP15 -> -71862 | AS15: =IFERROR(AR15/AP15,0) -> -0.026917379 | AT15: =SUM(AT8,AT9,AT10,AT11,AT12,AT13,AT14) -> 3118825 | AU15: =SUM(AU8,AU9,AU10,AU11,AU12,AU13,AU14) -> 3049681 | AV15: =AU15-AT15 -> -69144 | AW15: =IFERROR(AV15/AT15,0) -> -0.022169888
A16: Profit | B16: =B6-B15 -> -2483908 | C16: =C6-C15 -> -2531155 | D16: =C16-B16 -> -47247 | E16: =IFERROR(D16/B16,0) -> 0.019021236 | F16: =F6-F15 -> -1985474 | G16: =G6-G15 -> -2012648 | H16: =G16-F16 -> -27174 | I16: =IFERROR(H16/F16,0) -> 0.013686404 | J16: =J6-J15 -> -2533154 | K16: =K6-K15 -> -2615788 | L16: =K16-J16 -> -82634 | M16: =IFERROR(L16/J16,0) -> 0.032620993 | N16: =N6-N15 -> -2650726 | O16: =O6-O15 -> -2727507 | P16: =O16-N16 -> -76781 | Q16: =IFERROR(P16/N16,0) -> 0.028966027 | R16: =R6-R15 -> -334163 | S16: =S6-S15 -> -372046 | T16: =S16-R16 -> -37883 | U16: =IFERROR(T16/R16,0) -> 0.11336683 | V16: =V6-V15 -> -936689 | W16: =W6-W15 -> -934733 | X16: =W16-V16 -> 1956 | Y16: =IFERROR(X16/V16,0) -> -0.0020882064 | Z16: =Z6-Z15 -> -1504240 | AA16: =AA6-AA15 -> -1592112 | AB16: =AA16-Z16 -> -87872 | AC16: =IFERROR(AB16/Z16,0) -> 0.05841621 | AD16: =AD6-AD15 -> -1137213 | AE16: =AE6-AE15 -> -1149166 | AF16: =AE16-AD16 -> -11953 | AG16: =IFERROR(AF16/AD16,0) -> 0.010510784 | AH16: =AH6-AH15 -> 102846 | AI16: =AI6-AI15 -> 106980 | AJ16: =AI16-AH16 -> 4134 | AK16: =IFERROR(AJ16/AH16,0) -> 0.040196021 | AL16: =AL6-AL15 -> -2121690 | AM16: =AM6-AM15 -> -2029835 | AN16: =AM16-AL16 -> 91855 | AO16: =IFERROR(AN16/AL16,0) -> -0.043293318 | AP16: =AP6-AP15 -> -2595447 | AQ16: =AQ6-AQ15 -> -2519773 | AR16: =AQ16-AP16 -> 75674 | AS16: =IFERROR(AR16/AP16,0) -> -0.029156442 | AT16: =AT6-AT15 -> -3056375 | AU16: =AU6-AU15 -> -2990607 | AV16: =AU16-AT16 -> 65768 | AW16: =IFERROR(AV16/AT16,0) -> -0.021518302
A17: Profit Margin % | B17: =IFERROR(B16/B6,0) -> -8.7430456 | C17: =IFERROR(C16/C6,0) -> -9.447781 | D17: =C17-B17 -> -0.70473536 | F17: =IFERROR(F16/F6,0) -> -37.613648 | G17: =IFERROR(G16/G6,0) -> -39.521031 | H17: =G17-F17 -> -1.907383 | J17: =IFERROR(J16/J6,0) -> -47.997309 | K17: =IFERROR(K16/K6,0) -> -49.343318 | L17: =K17-J17 -> -1.3460091 | N17: =IFERROR(N16/N6,0) -> -142.35143 | O17: =IFERROR(O16/O6,0) -> -148.29855 | P17: =O17-N17 -> -5.9471225 | R17: =IFERROR(R16/R6,0) -> -0.5339082 | S17: =IFERROR(S16/S6,0) -> -0.61764623 | T17: =S17-R17 -> -0.083738026 | V17: =IFERROR(V16/V6,0) -> -3.274999 | W17: =IFERROR(W16/W6,0) -> -3.2036638 | X17: =W17-V17 -> 0.071335106 | Z17: =IFERROR(Z16/Z6,0) -> -3.9259205 | AA17: =IFERROR(AA16/AA6,0) -> -4.4436158 | AB17: =AA17-Z17 -> -0.51769531 | AD17: =IFERROR(AD16/AD6,0) -> -175.68562 | AE17: =IFERROR(AE16/AE6,0) -> -184.45682 | AF17: =AE17-AD17 -> -8.7712047 | AH17: =IFERROR(AH16/AH6,0) -> 0.094329637 | AI17: =IFERROR(AI16/AI6,0) -> 0.10053982 | AJ17: =AI17-AH17 -> 0.0062101839 | AL17: =IFERROR(AL16/AL6,0) -> -3.8165109 | AM17: =IFERROR(AM16/AM6,0) -> -3.6803843 | AN17: =AM17-AL17 -> 0.13612658 | AP17: =IFERROR(AP16/AP6,0) -> -34.942338 | AQ17: =IFERROR(AQ16/AQ6,0) -> -32.26755 | AR17: =AQ17-AP17 -> 2.674788 | AT17: =IFERROR(AT16/AT6,0) -> -48.941153 | AU17: =IFERROR(AU16/AU6,0) -> -50.624759 | AV17: =AU17-AT17 -> -1.6836059

Sheet 3-Month Forecast
A1: 3-Month Rolling Forecast
A3: Assumption | B3: Monthly Growth Rate | C3: 0.05 | D3: ← Blue/yellow = key assumption (editable)
A5: Period | B5: Type | C5: Revenue | D5: Total Costs | E5: Profit | F5: Profit Margin %
A6: Oct-2024 | B6: Actual | C6: ='Monthly P&L'!AM6 -> 551528 | D6: ='Monthly P&L'!AM15 -> 2581363 | E6: =C6-D6 -> -2029835 | F6: =IFERROR(E6/C6,0) -> -3.6803843
A7: Nov-2024 | B7: Actual | C7: ='Monthly P&L'!AQ6 -> 78090 | D7: ='Monthly P&L'!AQ15 -> 2597863 | E7: =C7-D7 -> -2519773 | F7: =IFERROR(E7/C7,0) -> -32.26755
A8: Dec-2024 | B8: Actual | C8: ='Monthly P&L'!AU6 -> 59074 | D8: ='Monthly P&L'!AU15 -> 3049681 | E8: =C8-D8 -> -2990607 | F8: =IFERROR(E8/C8,0) -> -50.624759
A9: Jan-2025 | B9: Forecast | C9: =AVERAGE(C6:C8)*(1+$C$3) -> 241042.2 | D9: =AVERAGE(D6:D8)*(1+$C$3) -> 2880117.5 | E9: =C9-D9 -> -2639075.2 | F9: =IFERROR(E9/C9,0) -> -10.948603
A10: Feb-2025 | B10: Forecast | C10: =AVERAGE(C7:C9)*(1+$C$3) -> 132372.17 | D10: =AVERAGE(D7:D9)*(1+$C$3) -> 2984681.5 | E10: =C10-D10 -> -2852309.3 | F10: =IFERROR(E10/C10,0) -> -21.547651
A11: Mar-2025 | B11: Forecast | C11: =AVERAGE(C8:C10)*(1+$C$3) -> 151370.93 | D11: =AVERAGE(D8:D10)*(1+$C$3) -> 3120068 | E11: =C11-D11 -> -2968697.1 | F11: =IFERROR(E11/C11,0) -> -19.612069
A13: Methodology
A14: • Historical rows pull Actuals from the Monthly P&L tab.
A15: • Forecast = trailing 3-month average × (1 + monthly growth rate).
A16: • Change the growth rate in cell C3 (yellow) to flex the forecast.
A17: • Revenue = Sales department. Costs = sum of all non-Sales departments.
